{
  "n_topics": 10,
  "topic_coordinates": [
    {
      "topic": 1,
      "x": 13.8347,
      "y": -3.8487,
      "freq": 12.1236
    },
    {
      "topic": 2,
      "x": 54.5013,
      "y": -27.1242,
      "freq": 0.5378
    },
    {
      "topic": 3,
      "x": -49.6725,
      "y": -18.6517,
      "freq": 5.8937
    },
    {
      "topic": 4,
      "x": 38.6009,
      "y": 82.6543,
      "freq": 6.5253
    },
    {
      "topic": 5,
      "x": -23.8275,
      "y": 21.7521,
      "freq": 7.8098
    },
    {
      "topic": 6,
      "x": -65.7592,
      "y": 41.69,
      "freq": 13.3775
    },
    {
      "topic": 7,
      "x": -20.5147,
      "y": 76.3874,
      "freq": 20.2871
    },
    {
      "topic": 8,
      "x": 64.3071,
      "y": 26.9731,
      "freq": 9.7671
    },
    {
      "topic": 9,
      "x": 17.2424,
      "y": 41.6501,
      "freq": 20.5841
    },
    {
      "topic": 10,
      "x": -4.0917,
      "y": -47.5903,
      "freq": 3.094
    }
  ],
  "default_term_freq": [
    {
      "term": "nationalsozialismus",
      "freq": 64.0,
      "total": 64.0
    },
    {
      "term": "versus",
      "freq": 28.0,
      "total": 28.0
    },
    {
      "term": "sozialisation",
      "freq": 20.0,
      "total": 20.0
    },
    {
      "term": "gesellschaftlich",
      "freq": 28.0,
      "total": 28.0
    },
    {
      "term": "demokratisch",
      "freq": 18.0,
      "total": 18.0
    },
    {
      "term": "möglichkeit",
      "freq": 18.0,
      "total": 18.0
    },
    {
      "term": "analyse",
      "freq": 29.0,
      "total": 29.0
    },
    {
      "term": "demokratie",
      "freq": 48.0,
      "total": 48.0
    },
    {
      "term": "kulturell",
      "freq": 21.0,
      "total": 21.0
    },
    {
      "term": "historisch",
      "freq": 18.0,
      "total": 18.0
    },
    {
      "term": "nationalsozialistisch",
      "freq": 21.0,
      "total": 21.0
    },
    {
      "term": "diskriminierung",
      "freq": 20.0,
      "total": 20.0
    },
    {
      "term": "heutig",
      "freq": 16.0,
      "total": 16.0
    },
    {
      "term": "auseinandersetzung",
      "freq": 23.0,
      "total": 23.0
    },
    {
      "term": "frieden",
      "freq": 15.0,
      "total": 15.0
    },
    {
      "term": "bezug",
      "freq": 15.0,
      "total": 15.0
    },
    {
      "term": "perspektive",
      "freq": 17.0,
      "total": 17.0
    },
    {
      "term": "kompetenz",
      "freq": 19.0,
      "total": 19.0
    },
    {
      "term": "politisch",
      "freq": 35.0,
      "total": 35.0
    },
    {
      "term": "antisemitismus",
      "freq": 57.0,
      "total": 57.0
    },
    {
      "term": "international",
      "freq": 16.0,
      "total": 16.0
    },
    {
      "term": "menschenrecht",
      "freq": 13.0,
      "total": 13.0
    },
    {
      "term": "ideologie",
      "freq": 19.0,
      "total": 19.0
    },
    {
      "term": "umgang",
      "freq": 14.0,
      "total": 14.0
    },
    {
      "term": "nsdiktatur",
      "freq": 25.0,
      "total": 25.0
    },
    {
      "term": "verschieden",
      "freq": 17.0,
      "total": 17.0
    },
    {
      "term": "volksgemeinschaft",
      "freq": 18.0,
      "total": 18.0
    },
    {
      "term": "theorie",
      "freq": 18.0,
      "total": 18.0
    },
    {
      "term": "diversität",
      "freq": 17.0,
      "total": 17.0
    },
    {
      "term": "führerprinzip",
      "freq": 15.0,
      "total": 15.0
    }
  ],
  "topics": {
    "1": [
      {
        "term": "frieden",
        "freq": 14.81,
        "total": 15.93,
        "logprob": -2.9505,
        "loglift": 2.0372
      },
      {
        "term": "grundrecht",
        "freq": 8.12,
        "total": 9.25,
        "logprob": -3.5509,
        "loglift": 1.9803
      },
      {
        "term": "fachintern",
        "freq": 7.38,
        "total": 9.04,
        "logprob": -3.6469,
        "loglift": 1.9069
      },
      {
        "term": "ökonomisch",
        "freq": 9.35,
        "total": 11.64,
        "logprob": -3.4106,
        "loglift": 1.891
      },
      {
        "term": "grundgesetz",
        "freq": 9.56,
        "total": 12.47,
        "logprob": -3.3883,
        "loglift": 1.8439
      },
      {
        "term": "kulturell",
        "freq": 14.47,
        "total": 21.14,
        "logprob": -2.9737,
        "loglift": 1.7307
      },
      {
        "term": "struktur",
        "freq": 2.13,
        "total": 3.25,
        "logprob": -4.8895,
        "loglift": 1.6887
      },
      {
        "term": "interesse",
        "freq": 2.13,
        "total": 3.25,
        "logprob": -4.8895,
        "loglift": 1.6886
      },
      {
        "term": "mensch",
        "freq": 10.4,
        "total": 16.7,
        "logprob": -3.304,
        "loglift": 1.6361
      },
      {
        "term": "ergebnis",
        "freq": 1.79,
        "total": 2.9,
        "logprob": -5.0646,
        "loglift": 1.627
      },
      {
        "term": "krieg",
        "freq": 9.08,
        "total": 14.95,
        "logprob": -3.4394,
        "loglift": 1.612
      },
      {
        "term": "nationalistisch",
        "freq": 1.76,
        "total": 2.9,
        "logprob": -5.0832,
        "loglift": 1.6095
      },
      {
        "term": "migration",
        "freq": 8.62,
        "total": 14.52,
        "logprob": -3.4916,
        "loglift": 1.5886
      },
      {
        "term": "international",
        "freq": 9.5,
        "total": 16.05,
        "logprob": -3.3948,
        "loglift": 1.585
      },
      {
        "term": "betroffener",
        "freq": 7.79,
        "total": 13.31,
        "logprob": -3.5934,
        "loglift": 1.5738
      },
      {
        "term": "ursache",
        "freq": 10.66,
        "total": 18.78,
        "logprob": -3.2792,
        "loglift": 1.5437
      },
      {
        "term": "legitimität",
        "freq": 7.1,
        "total": 12.84,
        "logprob": -3.686,
        "loglift": 1.517
      },
      {
        "term": "teilhabe",
        "freq": 6.92,
        "total": 13.25,
        "logprob": -3.7118,
        "loglift": 1.4601
      },
      {
        "term": "fachbegriff",
        "freq": 6.88,
        "total": 13.46,
        "logprob": -3.7173,
        "loglift": 1.4386
      },
      {
        "term": "auswirkung",
        "freq": 7.09,
        "total": 14.28,
        "logprob": -3.6877,
        "loglift": 1.4093
      },
      {
        "term": "engagement",
        "freq": 7.23,
        "total": 14.68,
        "logprob": -3.6681,
        "loglift": 1.4009
      },
      {
        "term": "religiös",
        "freq": 3.13,
        "total": 6.59,
        "logprob": -4.506,
        "loglift": 1.3642
      },
      {
        "term": "kompetenz",
        "freq": 9.05,
        "total": 19.11,
        "logprob": -3.4434,
        "loglift": 1.3621
      },
      {
        "term": "bezug",
        "freq": 6.99,
        "total": 15.85,
        "logprob": -3.7007,
        "loglift": 1.2917
      },
      {
        "term": "demokratisch",
        "freq": 7.76,
        "total": 18.83,
        "logprob": -3.597,
        "loglift": 1.2233
      },
      {
        "term": "notwendigkeit",
        "freq": 1.29,
        "total": 3.16,
        "logprob": -5.3882,
        "loglift": 1.2167
      },
      {
        "term": "ungleichheit",
        "freq": 1.1,
        "total": 2.71,
        "logprob": -5.5479,
        "loglift": 1.2125
      },
      {
        "term": "diversität",
        "freq": 6.76,
        "total": 17.83,
        "logprob": -3.7349,
        "loglift": 1.1402
      },
      {
        "term": "konflikt",
        "freq": 3.1,
        "total": 8.28,
        "logprob": -4.5156,
        "loglift": 1.1266
      },
      {
        "term": "geschichte",
        "freq": 2.17,
        "total": 5.83,
        "logprob": -4.8721,
        "loglift": 1.12
      },
      {
        "term": "gewalt",
        "freq": 7.34,
        "total": 20.84,
        "logprob": -3.6519,
        "loglift": 1.067
      },
      {
        "term": "demokratie",
        "freq": 8.49,
        "total": 48.95,
        "logprob": -3.5072,
        "loglift": 0.3577
      },
      {
        "term": "nationalsozialismus",
        "freq": 6.91,
        "total": 64.23,
        "logprob": -3.713,
        "loglift": -0.1197
      },
      {
        "term": "rassistisch",
        "freq": 3.21,
        "total": 15.38,
        "logprob": -4.4809,
        "loglift": 0.5418
      },
      {
        "term": "politisch",
        "freq": 3.69,
        "total": 35.23,
        "logprob": -4.3402,
        "loglift": -0.1462
      },
      {
        "term": "leben",
        "freq": 2.34,
        "total": 12.2,
        "logprob": -4.7976,
        "loglift": 0.4571
      }
    ],
    "2": [
      {
        "term": "quantitativ",
        "freq": 0.06,
        "total": 2.27,
        "logprob": -5.4184,
        "loglift": 1.5167
      },
      {
        "term": "lernorte",
        "freq": 0.06,
        "total": 2.32,
        "logprob": -5.3996,
        "loglift": 1.5165
      },
      {
        "term": "frei",
        "freq": 0.06,
        "total": 2.3,
        "logprob": -5.4263,
        "loglift": 1.4965
      },
      {
        "term": "arbeitsteilig",
        "freq": 0.05,
        "total": 2.28,
        "logprob": -5.4385,
        "loglift": 1.495
      },
      {
        "term": "differenzierung",
        "freq": 0.05,
        "total": 2.28,
        "logprob": -5.4382,
        "loglift": 1.4949
      },
      {
        "term": "fakultativ",
        "freq": 0.05,
        "total": 2.27,
        "logprob": -5.446,
        "loglift": 1.491
      },
      {
        "term": "webquest",
        "freq": 0.06,
        "total": 2.57,
        "logprob": -5.4071,
        "loglift": 1.4055
      },
      {
        "term": "musik",
        "freq": 0.05,
        "total": 2.53,
        "logprob": -5.439,
        "loglift": 1.3892
      },
      {
        "term": "gerichtsverhandlung",
        "freq": 0.05,
        "total": 2.55,
        "logprob": -5.4366,
        "loglift": 1.3835
      },
      {
        "term": "ungleichheit",
        "freq": 0.05,
        "total": 2.71,
        "logprob": -5.4393,
        "loglift": 1.321
      },
      {
        "term": "ergebnis",
        "freq": 0.05,
        "total": 2.9,
        "logprob": -5.4492,
        "loglift": 1.2424
      },
      {
        "term": "nationalistisch",
        "freq": 0.05,
        "total": 2.9,
        "logprob": -5.4561,
        "loglift": 1.2366
      },
      {
        "term": "recherche",
        "freq": 0.05,
        "total": 2.94,
        "logprob": -5.4533,
        "loglift": 1.2224
      },
      {
        "term": "wandel",
        "freq": 0.05,
        "total": 2.98,
        "logprob": -5.4439,
        "loglift": 1.2209
      },
      {
        "term": "vergleich",
        "freq": 0.05,
        "total": 3.05,
        "logprob": -5.4519,
        "loglift": 1.1886
      },
      {
        "term": "recherch",
        "freq": 0.05,
        "total": 3.15,
        "logprob": -5.4606,
        "loglift": 1.1487
      },
      {
        "term": "interesse",
        "freq": 0.05,
        "total": 3.25,
        "logprob": -5.4386,
        "loglift": 1.1394
      },
      {
        "term": "notwendigkeit",
        "freq": 0.05,
        "total": 3.16,
        "logprob": -5.4671,
        "loglift": 1.1378
      },
      {
        "term": "struktur",
        "freq": 0.05,
        "total": 3.25,
        "logprob": -5.4581,
        "loglift": 1.1202
      },
      {
        "term": "erziehung",
        "freq": 0.05,
        "total": 3.38,
        "logprob": -5.4434,
        "loglift": 1.0942
      },
      {
        "term": "wirksamkeit",
        "freq": 0.06,
        "total": 3.51,
        "logprob": -5.4264,
        "loglift": 1.0742
      },
      {
        "term": "gemeinschaft",
        "freq": 0.06,
        "total": 3.53,
        "logprob": -5.4303,
        "loglift": 1.0637
      },
      {
        "term": "rechtsextremismus",
        "freq": 0.06,
        "total": 3.66,
        "logprob": -5.4174,
        "loglift": 1.0417
      },
      {
        "term": "system",
        "freq": 0.06,
        "total": 3.8,
        "logprob": -5.3879,
        "loglift": 1.0336
      },
      {
        "term": "methode",
        "freq": 0.06,
        "total": 3.7,
        "logprob": -5.4271,
        "loglift": 1.0209
      },
      {
        "term": "integration",
        "freq": 0.05,
        "total": 3.74,
        "logprob": -5.4324,
        "loglift": 1.0044
      },
      {
        "term": "bundesrepublik",
        "freq": 0.06,
        "total": 3.78,
        "logprob": -5.4293,
        "loglift": 0.9978
      },
      {
        "term": "kolonie",
        "freq": 0.05,
        "total": 3.79,
        "logprob": -5.4541,
        "loglift": 0.9687
      },
      {
        "term": "kennen",
        "freq": 0.06,
        "total": 4.0,
        "logprob": -5.427,
        "loglift": 0.9414
      },
      {
        "term": "aktiv",
        "freq": 0.05,
        "total": 4.07,
        "logprob": -5.4312,
        "loglift": 0.9202
      },
      {
        "term": "motiv",
        "freq": 0.06,
        "total": 4.59,
        "logprob": -5.3915,
        "loglift": 0.8395
      },
      {
        "term": "erhalt",
        "freq": 0.06,
        "total": 4.48,
        "logprob": -5.4124,
        "loglift": 0.8434
      },
      {
        "term": "grundlegend",
        "freq": 0.06,
        "total": 5.72,
        "logprob": -5.3802,
        "loglift": 0.6315
      },
      {
        "term": "medium",
        "freq": 0.06,
        "total": 4.45,
        "logprob": -5.4185,
        "loglift": 0.845
      },
      {
        "term": "anregung",
        "freq": 0.06,
        "total": 4.35,
        "logprob": -5.4226,
        "loglift": 0.864
      },
      {
        "term": "republik",
        "freq": 0.06,
        "total": 5.35,
        "logprob": -5.3999,
        "loglift": 0.6779
      },
      {
        "term": "ordnung",
        "freq": 0.06,
        "total": 5.8,
        "logprob": -5.395,
        "loglift": 0.6036
      },
      {
        "term": "beurteilen",
        "freq": 0.06,
        "total": 6.03,
        "logprob": -5.3932,
        "loglift": 0.5654
      },
      {
        "term": "religiös",
        "freq": 0.06,
        "total": 6.59,
        "logprob": -5.3885,
        "loglift": 0.4817
      },
      {
        "term": "weimarer",
        "freq": 0.06,
        "total": 6.17,
        "logprob": -5.3946,
        "loglift": 0.5413
      },
      {
        "term": "ziel",
        "freq": 0.06,
        "total": 6.02,
        "logprob": -5.3966,
        "loglift": 0.5639
      },
      {
        "term": "machtergreifung",
        "freq": 0.06,
        "total": 5.54,
        "logprob": -5.4035,
        "loglift": 0.6394
      },
      {
        "term": "erläutern",
        "freq": 0.06,
        "total": 5.5,
        "logprob": -5.406,
        "loglift": 0.6455
      },
      {
        "term": "kritisch",
        "freq": 0.06,
        "total": 4.87,
        "logprob": -5.4138,
        "loglift": 0.7584
      },
      {
        "term": "mangelnd",
        "freq": 0.06,
        "total": 5.15,
        "logprob": -5.4135,
        "loglift": 0.7027
      },
      {
        "term": "herrschaft",
        "freq": 0.06,
        "total": 13.4,
        "logprob": -5.3689,
        "loglift": -0.2085
      },
      {
        "term": "analysieren",
        "freq": 0.06,
        "total": 17.96,
        "logprob": -5.3588,
        "loglift": -0.4911
      },
      {
        "term": "europäisch",
        "freq": 0.06,
        "total": 6.91,
        "logprob": -5.4017,
        "loglift": 0.4215
      },
      {
        "term": "nationalsozialismus",
        "freq": 0.06,
        "total": 64.23,
        "logprob": -5.3143,
        "loglift": -1.721
      },
      {
        "term": "bewert",
        "freq": 0.06,
        "total": 18.86,
        "logprob": -5.3623,
        "loglift": -0.5438
      },
      {
        "term": "weltkrieg",
        "freq": 0.06,
        "total": 23.38,
        "logprob": -5.3596,
        "loglift": -0.7558
      },
      {
        "term": "thema",
        "freq": 0.06,
        "total": 14.48,
        "logprob": -5.3794,
        "loglift": -0.2963
      },
      {
        "term": "projekt",
        "freq": 0.06,
        "total": 11.4,
        "logprob": -5.3868,
        "loglift": -0.0642
      },
      {
        "term": "imperialismus",
        "freq": 0.06,
        "total": 13.68,
        "logprob": -5.3825,
        "loglift": -0.2423
      },
      {
        "term": "lebensraum",
        "freq": 0.06,
        "total": 11.11,
        "logprob": -5.396,
        "loglift": -0.0482
      },
      {
        "term": "ökonomisch",
        "freq": 0.06,
        "total": 11.64,
        "logprob": -5.3969,
        "loglift": -0.0953
      },
      {
        "term": "europa",
        "freq": 0.06,
        "total": 20.65,
        "logprob": -5.3919,
        "loglift": -0.664
      },
      {
        "term": "zwischenkriegszeit",
        "freq": 0.06,
        "total": 11.62,
        "logprob": -5.3985,
        "loglift": -0.0958
      },
      {
        "term": "handeln",
        "freq": 0.06,
        "total": 7.87,
        "logprob": -5.4079,
        "loglift": 0.2853
      },
      {
        "term": "osten",
        "freq": 0.06,
        "total": 5.79,
        "logprob": -5.4115,
        "loglift": 0.5879
      },
      {
        "term": "demokratie",
        "freq": 0.06,
        "total": 48.95,
        "logprob": -5.4,
        "loglift": -1.5351
      },
      {
        "term": "volksgemeinschaft",
        "freq": 0.06,
        "total": 18.42,
        "logprob": -5.4026,
        "loglift": -0.5602
      },
      {
        "term": "perspektive",
        "freq": 0.06,
        "total": 17.29,
        "logprob": -5.4042,
        "loglift": -0.4984
      },
      {
        "term": "diktatur",
        "freq": 0.06,
        "total": 23.0,
        "logprob": -5.4042,
        "loglift": -0.784
      },
      {
        "term": "ideologisch",
        "freq": 0.06,
        "total": 22.12,
        "logprob": -5.4045,
        "loglift": -0.7453
      }
    ],
    "3": [
      {
        "term": "partizipation",
        "freq": 6.31,
        "total": 7.53,
        "logprob": -3.0827,
        "loglift": 2.6544
      },
      {
        "term": "leer",
        "freq": 5.85,
        "total": 6.99,
        "logprob": -3.1576,
        "loglift": 2.6531
      },
      {
        "term": "bleiben",
        "freq": 5.85,
        "total": 7.01,
        "logprob": -3.1574,
        "loglift": 2.6514
      },
      {
        "term": "sozialisation",
        "freq": 15.3,
        "total": 20.81,
        "logprob": -2.1964,
        "loglift": 2.5241
      },
      {
        "term": "emanzipation",
        "freq": 5.34,
        "total": 8.1,
        "logprob": -3.2491,
        "loglift": 2.415
      },
      {
        "term": "wert",
        "freq": 5.59,
        "total": 10.93,
        "logprob": -3.2034,
        "loglift": 2.1607
      },
      {
        "term": "gruppe",
        "freq": 5.58,
        "total": 11.61,
        "logprob": -3.205,
        "loglift": 2.0991
      },
      {
        "term": "bezug",
        "freq": 7.6,
        "total": 15.85,
        "logprob": -2.8959,
        "loglift": 2.0965
      },
      {
        "term": "gerechtigkeit",
        "freq": 5.32,
        "total": 11.24,
        "logprob": -3.2534,
        "loglift": 2.0827
      },
      {
        "term": "umgang",
        "freq": 6.61,
        "total": 14.81,
        "logprob": -3.0353,
        "loglift": 2.0252
      },
      {
        "term": "gesellschaftlich",
        "freq": 12.44,
        "total": 28.51,
        "logprob": -2.4032,
        "loglift": 2.0024
      },
      {
        "term": "fachbegriff",
        "freq": 5.52,
        "total": 13.46,
        "logprob": -3.2155,
        "loglift": 1.9404
      },
      {
        "term": "kompetenz",
        "freq": 6.3,
        "total": 19.11,
        "logprob": -3.0841,
        "loglift": 1.7213
      },
      {
        "term": "diskriminierung",
        "freq": 6.37,
        "total": 20.4,
        "logprob": -3.0729,
        "loglift": 1.6674
      },
      {
        "term": "diversität",
        "freq": 5.42,
        "total": 17.83,
        "logprob": -3.2349,
        "loglift": 1.6402
      },
      {
        "term": "verschieden",
        "freq": 5.33,
        "total": 17.6,
        "logprob": -3.2503,
        "loglift": 1.6376
      },
      {
        "term": "wandel",
        "freq": 0.79,
        "total": 2.98,
        "logprob": -5.1634,
        "loglift": 1.5015
      },
      {
        "term": "kulturell",
        "freq": 5.59,
        "total": 21.14,
        "logprob": -3.2032,
        "loglift": 1.5012
      },
      {
        "term": "integration",
        "freq": 0.9,
        "total": 3.74,
        "logprob": -5.0296,
        "loglift": 1.4072
      },
      {
        "term": "sozial",
        "freq": 1.73,
        "total": 7.62,
        "logprob": -4.374,
        "loglift": 1.351
      },
      {
        "term": "ungleichheit",
        "freq": 0.55,
        "total": 2.71,
        "logprob": -5.5257,
        "loglift": 1.2347
      },
      {
        "term": "erziehung",
        "freq": 0.63,
        "total": 3.38,
        "logprob": -5.3864,
        "loglift": 1.1512
      },
      {
        "term": "geschichte",
        "freq": 0.98,
        "total": 5.83,
        "logprob": -4.9437,
        "loglift": 1.0484
      },
      {
        "term": "musik",
        "freq": 0.38,
        "total": 2.53,
        "logprob": -5.8914,
        "loglift": 0.9368
      },
      {
        "term": "medium",
        "freq": 0.45,
        "total": 4.45,
        "logprob": -5.7131,
        "loglift": 0.5504
      },
      {
        "term": "zukunft",
        "freq": 0.41,
        "total": 4.14,
        "logprob": -5.8079,
        "loglift": 0.5266
      },
      {
        "term": "maßnahme",
        "freq": 0.56,
        "total": 6.96,
        "logprob": -5.5064,
        "loglift": 0.3096
      },
      {
        "term": "rechtsextremismus",
        "freq": 0.28,
        "total": 3.66,
        "logprob": -6.1974,
        "loglift": 0.2617
      },
      {
        "term": "fachintern",
        "freq": 0.59,
        "total": 9.04,
        "logprob": -5.4512,
        "loglift": 0.1027
      },
      {
        "term": "antidemokratisch",
        "freq": 0.3,
        "total": 4.8,
        "logprob": -6.1285,
        "loglift": 0.0589
      },
      {
        "term": "grenze",
        "freq": 0.31,
        "total": 5.4,
        "logprob": -6.1108,
        "loglift": -0.0422
      },
      {
        "term": "politisch",
        "freq": 0.46,
        "total": 35.23,
        "logprob": -5.7108,
        "loglift": -1.5168
      }
    ],
    "4": [
      {
        "term": "beispiel",
        "freq": 7.08,
        "total": 8.17,
        "logprob": -3.0694,
        "loglift": 2.5864
      },
      {
        "term": "kinderarbeit",
        "freq": 6.4,
        "total": 7.41,
        "logprob": -3.1706,
        "loglift": 2.5822
      },
      {
        "term": "menschenwürde",
        "freq": 6.98,
        "total": 8.15,
        "logprob": -3.0838,
        "loglift": 2.5735
      },
      {
        "term": "menschenrechtsverletzung",
        "freq": 5.62,
        "total": 6.64,
        "logprob": -3.3005,
        "loglift": 2.5625
      },
      {
        "term": "grundbegriff",
        "freq": 4.81,
        "total": 5.85,
        "logprob": -3.4566,
        "loglift": 2.5329
      },
      {
        "term": "güterabwägung",
        "freq": 4.06,
        "total": 5.08,
        "logprob": -3.6242,
        "loglift": 2.5072
      },
      {
        "term": "todesstrafe",
        "freq": 4.07,
        "total": 5.08,
        "logprob": -3.6237,
        "loglift": 2.5068
      },
      {
        "term": "grundbedürfnisse",
        "freq": 4.06,
        "total": 5.08,
        "logprob": -3.6239,
        "loglift": 2.5068
      },
      {
        "term": "verletzung",
        "freq": 4.06,
        "total": 5.08,
        "logprob": -3.6248,
        "loglift": 2.5064
      },
      {
        "term": "psychisch",
        "freq": 4.06,
        "total": 5.08,
        "logprob": -3.6241,
        "loglift": 2.5061
      },
      {
        "term": "folter",
        "freq": 4.06,
        "total": 5.08,
        "logprob": -3.6247,
        "loglift": 2.5061
      },
      {
        "term": "misshandlunge",
        "freq": 4.06,
        "total": 5.08,
        "logprob": -3.6249,
        "loglift": 2.5055
      },
      {
        "term": "katastrophenfälle",
        "freq": 4.06,
        "total": 5.08,
        "logprob": -3.625,
        "loglift": 2.5054
      },
      {
        "term": "physisch",
        "freq": 4.06,
        "total": 5.08,
        "logprob": -3.6253,
        "loglift": 2.5049
      },
      {
        "term": "hilfsaktion",
        "freq": 4.06,
        "total": 5.09,
        "logprob": -3.6243,
        "loglift": 2.5043
      },
      {
        "term": "produkt",
        "freq": 4.07,
        "total": 5.72,
        "logprob": -3.6238,
        "loglift": 2.3879
      },
      {
        "term": "diskutieren",
        "freq": 4.53,
        "total": 6.95,
        "logprob": -3.5148,
        "loglift": 2.3026
      },
      {
        "term": "menschenrecht",
        "freq": 7.95,
        "total": 13.33,
        "logprob": -2.9529,
        "loglift": 2.2126
      },
      {
        "term": "religiös",
        "freq": 2.51,
        "total": 6.59,
        "logprob": -4.1066,
        "loglift": 1.7636
      },
      {
        "term": "kultur",
        "freq": 3.61,
        "total": 10.06,
        "logprob": -3.742,
        "loglift": 1.7049
      },
      {
        "term": "international",
        "freq": 5.61,
        "total": 16.05,
        "logprob": -3.3015,
        "loglift": 1.6782
      },
      {
        "term": "leben",
        "freq": 2.74,
        "total": 12.2,
        "logprob": -4.0195,
        "loglift": 1.2352
      },
      {
        "term": "diskriminierung",
        "freq": 4.31,
        "total": 20.4,
        "logprob": -3.5652,
        "loglift": 1.1752
      },
      {
        "term": "form",
        "freq": 4.82,
        "total": 25.29,
        "logprob": -3.4543,
        "loglift": 1.0708
      },
      {
        "term": "frage",
        "freq": 2.51,
        "total": 16.92,
        "logprob": -4.1061,
        "loglift": 0.8212
      },
      {
        "term": "kompetenz",
        "freq": 2.79,
        "total": 19.11,
        "logprob": -3.9991,
        "loglift": 0.8063
      },
      {
        "term": "fakultativ",
        "freq": 0.17,
        "total": 2.27,
        "logprob": -6.7745,
        "loglift": 0.1626
      },
      {
        "term": "arbeitsteilig",
        "freq": 0.17,
        "total": 2.28,
        "logprob": -6.7777,
        "loglift": 0.1558
      },
      {
        "term": "lernorte",
        "freq": 0.18,
        "total": 2.32,
        "logprob": -6.7669,
        "loglift": 0.1491
      },
      {
        "term": "quantitativ",
        "freq": 0.17,
        "total": 2.27,
        "logprob": -6.7864,
        "loglift": 0.1487
      },
      {
        "term": "beschreiben",
        "freq": 0.31,
        "total": 4.23,
        "logprob": -6.1893,
        "loglift": 0.1244
      },
      {
        "term": "frei",
        "freq": 0.17,
        "total": 2.3,
        "logprob": -6.7753,
        "loglift": 0.1475
      },
      {
        "term": "integration",
        "freq": 0.19,
        "total": 3.74,
        "logprob": -6.6914,
        "loglift": -0.2547
      },
      {
        "term": "medium",
        "freq": 0.19,
        "total": 4.45,
        "logprob": -6.7094,
        "loglift": -0.4459
      },
      {
        "term": "jugendliche",
        "freq": 0.19,
        "total": 5.27,
        "logprob": -6.7036,
        "loglift": -0.6098
      },
      {
        "term": "nationalsozialismus",
        "freq": 0.19,
        "total": 64.23,
        "logprob": -6.6655,
        "loglift": -3.0722
      },
      {
        "term": "mensch",
        "freq": 0.19,
        "total": 16.7,
        "logprob": -6.6993,
        "loglift": -1.7591
      }
    ],
    "5": [
      {
        "term": "reich",
        "freq": 5.78,
        "total": 7.56,
        "logprob": -3.451,
        "loglift": 2.282
      },
      {
        "term": "grenze",
        "freq": 4.0,
        "total": 5.4,
        "logprob": -3.8187,
        "loglift": 2.2499
      },
      {
        "term": "lernen",
        "freq": 4.77,
        "total": 6.92,
        "logprob": -3.6447,
        "loglift": 2.1765
      },
      {
        "term": "kritisch",
        "freq": 3.12,
        "total": 4.87,
        "logprob": -4.0674,
        "loglift": 2.1047
      },
      {
        "term": "deutsch",
        "freq": 6.41,
        "total": 10.12,
        "logprob": -3.3488,
        "loglift": 2.0923
      },
      {
        "term": "lernziel",
        "freq": 3.9,
        "total": 6.29,
        "logprob": -3.8439,
        "loglift": 2.0724
      },
      {
        "term": "gegenwärtig",
        "freq": 3.37,
        "total": 5.5,
        "logprob": -3.9902,
        "loglift": 2.0617
      },
      {
        "term": "entwickeln",
        "freq": 2.83,
        "total": 4.76,
        "logprob": -4.1657,
        "loglift": 2.0295
      },
      {
        "term": "anregung",
        "freq": 2.56,
        "total": 4.35,
        "logprob": -4.2642,
        "loglift": 2.0224
      },
      {
        "term": "menschenverachtend",
        "freq": 2.55,
        "total": 4.66,
        "logprob": -4.2687,
        "loglift": 1.9471
      },
      {
        "term": "gesellschaft",
        "freq": 6.87,
        "total": 12.72,
        "logprob": -3.2789,
        "loglift": 1.9339
      },
      {
        "term": "nationalsozialistisch",
        "freq": 11.34,
        "total": 21.0,
        "logprob": -2.7776,
        "loglift": 1.9336
      },
      {
        "term": "populismus",
        "freq": 2.79,
        "total": 5.36,
        "logprob": -4.1784,
        "loglift": 1.8981
      },
      {
        "term": "erkennen",
        "freq": 2.53,
        "total": 5.33,
        "logprob": -4.278,
        "loglift": 1.8044
      },
      {
        "term": "zukunft",
        "freq": 1.93,
        "total": 4.14,
        "logprob": -4.5471,
        "loglift": 1.7873
      },
      {
        "term": "ideologie",
        "freq": 8.32,
        "total": 19.2,
        "logprob": -3.0871,
        "loglift": 1.7136
      },
      {
        "term": "aspekt",
        "freq": 2.78,
        "total": 6.64,
        "logprob": -4.183,
        "loglift": 1.6803
      },
      {
        "term": "ziel",
        "freq": 2.48,
        "total": 6.02,
        "logprob": -4.2983,
        "loglift": 1.6622
      },
      {
        "term": "sexismus",
        "freq": 1.82,
        "total": 4.75,
        "logprob": -4.609,
        "loglift": 1.5876
      },
      {
        "term": "antidemokratisch",
        "freq": 1.82,
        "total": 4.8,
        "logprob": -4.6048,
        "loglift": 1.5826
      },
      {
        "term": "integration",
        "freq": 1.4,
        "total": 3.74,
        "logprob": -4.8663,
        "loglift": 1.5705
      },
      {
        "term": "sozial",
        "freq": 2.69,
        "total": 7.62,
        "logprob": -4.2162,
        "loglift": 1.5088
      },
      {
        "term": "zusammenhang",
        "freq": 1.57,
        "total": 5.04,
        "logprob": -4.7561,
        "loglift": 1.3831
      },
      {
        "term": "weltdeutung",
        "freq": 3.86,
        "total": 13.91,
        "logprob": -3.8554,
        "loglift": 1.2681
      },
      {
        "term": "ausgrenzung",
        "freq": 1.82,
        "total": 7.05,
        "logprob": -4.6083,
        "loglift": 1.1948
      },
      {
        "term": "kennen",
        "freq": 1.0,
        "total": 4.0,
        "logprob": -5.2085,
        "loglift": 1.1599
      },
      {
        "term": "aktiv",
        "freq": 0.99,
        "total": 4.07,
        "logprob": -5.2136,
        "loglift": 1.1378
      },
      {
        "term": "rolle",
        "freq": 1.87,
        "total": 7.72,
        "logprob": -4.5784,
        "loglift": 1.1335
      },
      {
        "term": "demokratisch",
        "freq": 4.36,
        "total": 18.83,
        "logprob": -3.7324,
        "loglift": 1.0879
      },
      {
        "term": "grundlage",
        "freq": 3.41,
        "total": 18.23,
        "logprob": -3.9786,
        "loglift": 0.8743
      },
      {
        "term": "gesellschaftlich",
        "freq": 4.67,
        "total": 28.51,
        "logprob": -3.6647,
        "loglift": 0.7409
      },
      {
        "term": "lebensraum",
        "freq": 1.82,
        "total": 11.11,
        "logprob": -4.6074,
        "loglift": 0.7405
      },
      {
        "term": "antisemitismus",
        "freq": 4.44,
        "total": 57.65,
        "logprob": -3.7153,
        "loglift": -0.014
      },
      {
        "term": "sozialdarwinismus",
        "freq": 1.95,
        "total": 13.31,
        "logprob": -4.5378,
        "loglift": 0.6297
      },
      {
        "term": "inhalt",
        "freq": 2.19,
        "total": 22.46,
        "logprob": -4.4209,
        "loglift": 0.2231
      },
      {
        "term": "politisch",
        "freq": 2.17,
        "total": 35.23,
        "logprob": -4.4325,
        "loglift": -0.2385
      },
      {
        "term": "holocaust",
        "freq": 1.83,
        "total": 18.18,
        "logprob": -4.6024,
        "loglift": 0.2528
      },
      {
        "term": "widerstand",
        "freq": 1.83,
        "total": 20.14,
        "logprob": -4.6028,
        "loglift": 0.1504
      }
    ],
    "6": [
      {
        "term": "zwischenkriegszeit",
        "freq": 10.61,
        "total": 11.62,
        "logprob": -3.3828,
        "loglift": 1.9199
      },
      {
        "term": "führerprinzip",
        "freq": 13.25,
        "total": 15.89,
        "logprob": -3.16,
        "loglift": 1.8299
      },
      {
        "term": "machtergreifung",
        "freq": 4.54,
        "total": 5.54,
        "logprob": -4.2309,
        "loglift": 1.8121
      },
      {
        "term": "erläutern",
        "freq": 4.47,
        "total": 5.5,
        "logprob": -4.2474,
        "loglift": 1.8041
      },
      {
        "term": "volksgemeinschaft",
        "freq": 14.37,
        "total": 18.42,
        "logprob": -3.079,
        "loglift": 1.7634
      },
      {
        "term": "osten",
        "freq": 4.37,
        "total": 5.79,
        "logprob": -4.2698,
        "loglift": 1.7297
      },
      {
        "term": "lebensraum",
        "freq": 8.03,
        "total": 11.11,
        "logprob": -3.6613,
        "loglift": 1.6865
      },
      {
        "term": "verbrechen",
        "freq": 4.32,
        "total": 6.23,
        "logprob": -4.2816,
        "loglift": 1.6456
      },
      {
        "term": "herrschaftspraxis",
        "freq": 3.67,
        "total": 5.49,
        "logprob": -4.4429,
        "loglift": 1.6099
      },
      {
        "term": "nationalsozialismus",
        "freq": 42.76,
        "total": 64.23,
        "logprob": -1.9886,
        "loglift": 1.6047
      },
      {
        "term": "europa",
        "freq": 13.38,
        "total": 20.65,
        "logprob": -3.15,
        "loglift": 1.5779
      },
      {
        "term": "herrschaft",
        "freq": 8.62,
        "total": 13.4,
        "logprob": -3.5906,
        "loglift": 1.5699
      },
      {
        "term": "weltdeutung",
        "freq": 8.88,
        "total": 13.91,
        "logprob": -3.5608,
        "loglift": 1.5627
      },
      {
        "term": "bewert",
        "freq": 11.76,
        "total": 18.86,
        "logprob": -3.2793,
        "loglift": 1.5392
      },
      {
        "term": "charakterisieren",
        "freq": 10.45,
        "total": 16.78,
        "logprob": -3.3974,
        "loglift": 1.5383
      },
      {
        "term": "weimarer",
        "freq": 3.59,
        "total": 6.17,
        "logprob": -4.4649,
        "loglift": 1.471
      },
      {
        "term": "grundlage",
        "freq": 10.35,
        "total": 18.23,
        "logprob": -3.4075,
        "loglift": 1.4455
      },
      {
        "term": "militarismus",
        "freq": 3.24,
        "total": 5.84,
        "logprob": -4.568,
        "loglift": 1.4234
      },
      {
        "term": "republik",
        "freq": 2.85,
        "total": 5.35,
        "logprob": -4.697,
        "loglift": 1.3808
      },
      {
        "term": "verantwortung",
        "freq": 2.79,
        "total": 5.36,
        "logprob": -4.7166,
        "loglift": 1.3597
      },
      {
        "term": "sozialdarwinismus",
        "freq": 6.79,
        "total": 13.31,
        "logprob": -3.829,
        "loglift": 1.3385
      },
      {
        "term": "ideologisch",
        "freq": 10.97,
        "total": 22.12,
        "logprob": -3.3491,
        "loglift": 1.3102
      },
      {
        "term": "handeln",
        "freq": 3.67,
        "total": 7.87,
        "logprob": -4.4436,
        "loglift": 1.2496
      },
      {
        "term": "beschreiben",
        "freq": 1.94,
        "total": 4.23,
        "logprob": -5.0824,
        "loglift": 1.2312
      },
      {
        "term": "begründen",
        "freq": 2.79,
        "total": 6.39,
        "logprob": -4.7168,
        "loglift": 1.1849
      },
      {
        "term": "antidemokratisch",
        "freq": 1.88,
        "total": 4.8,
        "logprob": -5.1142,
        "loglift": 1.0731
      },
      {
        "term": "thema",
        "freq": 5.58,
        "total": 14.48,
        "logprob": -4.0256,
        "loglift": 1.0575
      },
      {
        "term": "antisemitismus",
        "freq": 18.61,
        "total": 57.65,
        "logprob": -2.8203,
        "loglift": 0.881
      },
      {
        "term": "ideologie",
        "freq": 5.65,
        "total": 19.2,
        "logprob": -4.0128,
        "loglift": 0.7878
      },
      {
        "term": "analysieren",
        "freq": 4.24,
        "total": 17.96,
        "logprob": -4.2995,
        "loglift": 0.5681
      },
      {
        "term": "diktatur",
        "freq": 4.48,
        "total": 23.0,
        "logprob": -4.244,
        "loglift": 0.3763
      },
      {
        "term": "weltkrieg",
        "freq": 4.31,
        "total": 23.38,
        "logprob": -4.2831,
        "loglift": 0.3206
      },
      {
        "term": "demokratie",
        "freq": 3.44,
        "total": 48.95,
        "logprob": -4.5076,
        "loglift": -0.6427
      },
      {
        "term": "nationalsozialistisch",
        "freq": 3.11,
        "total": 21.0,
        "logprob": -4.608,
        "loglift": 0.1032
      },
      {
        "term": "form",
        "freq": 2.88,
        "total": 25.29,
        "logprob": -4.6873,
        "loglift": -0.1621
      }
    ],
    "7": [
      {
        "term": "theorie",
        "freq": 17.53,
        "total": 18.62,
        "logprob": -3.2968,
        "loglift": 1.5348
      },
      {
        "term": "gegner",
        "freq": 16.86,
        "total": 17.96,
        "logprob": -3.3355,
        "loglift": 1.5321
      },
      {
        "term": "analyse",
        "freq": 27.41,
        "total": 29.44,
        "logprob": -2.8496,
        "loglift": 1.5239
      },
      {
        "term": "hinblick",
        "freq": 8.05,
        "total": 9.08,
        "logprob": -4.0754,
        "loglift": 1.4739
      },
      {
        "term": "ermitteln",
        "freq": 6.73,
        "total": 7.78,
        "logprob": -4.2539,
        "loglift": 1.4501
      },
      {
        "term": "versatzstück",
        "freq": 5.41,
        "total": 6.45,
        "logprob": -4.4717,
        "loglift": 1.4199
      },
      {
        "term": "ethnozentrismen",
        "freq": 5.42,
        "total": 6.46,
        "logprob": -4.4708,
        "loglift": 1.4198
      },
      {
        "term": "biologismus",
        "freq": 5.41,
        "total": 6.45,
        "logprob": -4.4719,
        "loglift": 1.4191
      },
      {
        "term": "chauvinismen",
        "freq": 5.41,
        "total": 6.46,
        "logprob": -4.4717,
        "loglift": 1.419
      },
      {
        "term": "typisch",
        "freq": 5.41,
        "total": 6.46,
        "logprob": -4.4716,
        "loglift": 1.4184
      },
      {
        "term": "erkenntnis",
        "freq": 5.37,
        "total": 6.43,
        "logprob": -4.4793,
        "loglift": 1.4159
      },
      {
        "term": "wissenschaftlich",
        "freq": 4.76,
        "total": 5.8,
        "logprob": -4.6008,
        "loglift": 1.3974
      },
      {
        "term": "modell",
        "freq": 4.76,
        "total": 5.8,
        "logprob": -4.6012,
        "loglift": 1.3967
      },
      {
        "term": "stehend",
        "freq": 4.75,
        "total": 5.8,
        "logprob": -4.6015,
        "loglift": 1.3959
      },
      {
        "term": "ordnung",
        "freq": 4.74,
        "total": 5.8,
        "logprob": -4.6055,
        "loglift": 1.3931
      },
      {
        "term": "rufen",
        "freq": 4.1,
        "total": 5.14,
        "logprob": -4.7504,
        "loglift": 1.3685
      },
      {
        "term": "staatlicher",
        "freq": 4.1,
        "total": 5.14,
        "logprob": -4.7505,
        "loglift": 1.3677
      },
      {
        "term": "demokratiebewusstsein",
        "freq": 4.09,
        "total": 5.14,
        "logprob": -4.7519,
        "loglift": 1.3675
      },
      {
        "term": "verfassung",
        "freq": 4.09,
        "total": 5.14,
        "logprob": -4.7523,
        "loglift": 1.3671
      },
      {
        "term": "richten",
        "freq": 4.09,
        "total": 5.14,
        "logprob": -4.7512,
        "loglift": 1.367
      },
      {
        "term": "karrierestreben",
        "freq": 4.09,
        "total": 5.14,
        "logprob": -4.7517,
        "loglift": 1.367
      },
      {
        "term": "sjg",
        "freq": 4.09,
        "total": 5.14,
        "logprob": -4.7513,
        "loglift": 1.367
      },
      {
        "term": "schwäche",
        "freq": 4.09,
        "total": 5.15,
        "logprob": -4.7515,
        "loglift": 1.3655
      },
      {
        "term": "mangelnd",
        "freq": 4.09,
        "total": 5.15,
        "logprob": -4.7514,
        "loglift": 1.3649
      },
      {
        "term": "funktion",
        "freq": 4.08,
        "total": 5.14,
        "logprob": -4.7556,
        "loglift": 1.3639
      },
      {
        "term": "nationalismus",
        "freq": 13.55,
        "total": 17.26,
        "logprob": -3.5545,
        "loglift": 1.3527
      },
      {
        "term": "frage",
        "freq": 13.19,
        "total": 16.92,
        "logprob": -3.5811,
        "loglift": 1.3462
      },
      {
        "term": "politisch",
        "freq": 27.39,
        "total": 35.23,
        "logprob": -2.8503,
        "loglift": 1.3437
      },
      {
        "term": "generell",
        "freq": 3.44,
        "total": 4.48,
        "logprob": -4.9244,
        "loglift": 1.3307
      },
      {
        "term": "gegeben",
        "freq": 3.44,
        "total": 4.48,
        "logprob": -4.9252,
        "loglift": 1.3306
      },
      {
        "term": "verbindung",
        "freq": 11.86,
        "total": 15.88,
        "logprob": -3.6876,
        "loglift": 1.3028
      },
      {
        "term": "denken",
        "freq": 9.31,
        "total": 13.0,
        "logprob": -3.9298,
        "loglift": 1.2606
      },
      {
        "term": "inhalt",
        "freq": 13.97,
        "total": 22.46,
        "logprob": -3.524,
        "loglift": 1.12
      },
      {
        "term": "unterschiedlich",
        "freq": 6.01,
        "total": 8.8,
        "logprob": -4.3675,
        "loglift": 1.2133
      },
      {
        "term": "führen",
        "freq": 5.4,
        "total": 7.83,
        "logprob": -4.4742,
        "loglift": 1.2237
      },
      {
        "term": "minderheit",
        "freq": 4.66,
        "total": 6.64,
        "logprob": -4.6209,
        "loglift": 1.2422
      },
      {
        "term": "stabilisierung",
        "freq": 4.66,
        "total": 6.65,
        "logprob": -4.6212,
        "loglift": 1.2393
      },
      {
        "term": "individuell",
        "freq": 4.5,
        "total": 6.27,
        "logprob": -4.6569,
        "loglift": 1.2636
      },
      {
        "term": "extremismus",
        "freq": 7.43,
        "total": 18.59,
        "logprob": -4.1551,
        "loglift": 0.6783
      },
      {
        "term": "vorurteil",
        "freq": 5.41,
        "total": 10.14,
        "logprob": -4.472,
        "loglift": 0.9671
      },
      {
        "term": "analysieren",
        "freq": 6.71,
        "total": 17.96,
        "logprob": -4.2574,
        "loglift": 0.6102
      },
      {
        "term": "stereotyp",
        "freq": 5.41,
        "total": 12.78,
        "logprob": -4.4716,
        "loglift": 0.736
      },
      {
        "term": "antisemitismus",
        "freq": 7.73,
        "total": 57.65,
        "logprob": -4.1154,
        "loglift": -0.414
      },
      {
        "term": "ideologisch",
        "freq": 5.73,
        "total": 22.12,
        "logprob": -4.4157,
        "loglift": 0.2436
      },
      {
        "term": "diktatur",
        "freq": 5.31,
        "total": 23.0,
        "logprob": -4.4901,
        "loglift": 0.1302
      },
      {
        "term": "krieg",
        "freq": 4.87,
        "total": 14.95,
        "logprob": -4.5785,
        "loglift": 0.4729
      }
    ],
    "8": [
      {
        "term": "versus",
        "freq": 26.96,
        "total": 28.09,
        "logprob": -2.1353,
        "loglift": 2.285
      },
      {
        "term": "arbeitsmigration",
        "freq": 9.3,
        "total": 10.45,
        "logprob": -3.1993,
        "loglift": 2.2098
      },
      {
        "term": "heutig",
        "freq": 13.72,
        "total": 16.18,
        "logprob": -2.8111,
        "loglift": 2.1611
      },
      {
        "term": "historisch",
        "freq": 14.77,
        "total": 18.03,
        "logprob": -2.7369,
        "loglift": 2.1266
      },
      {
        "term": "perspektive",
        "freq": 13.5,
        "total": 17.29,
        "logprob": -2.8268,
        "loglift": 2.079
      },
      {
        "term": "maßnahme",
        "freq": 5.31,
        "total": 6.96,
        "logprob": -3.7607,
        "loglift": 2.0553
      },
      {
        "term": "rom",
        "freq": 4.85,
        "total": 7.13,
        "logprob": -3.8509,
        "loglift": 1.9401
      },
      {
        "term": "sinto",
        "freq": 4.85,
        "total": 7.15,
        "logprob": -3.8514,
        "loglift": 1.9378
      },
      {
        "term": "rolle",
        "freq": 4.87,
        "total": 7.72,
        "logprob": -3.8457,
        "loglift": 1.8663
      },
      {
        "term": "recherch",
        "freq": 1.98,
        "total": 3.15,
        "logprob": -4.7469,
        "loglift": 1.8624
      },
      {
        "term": "recherche",
        "freq": 1.76,
        "total": 2.94,
        "logprob": -4.8667,
        "loglift": 1.8091
      },
      {
        "term": "webquest",
        "freq": 1.29,
        "total": 2.57,
        "logprob": -5.1744,
        "loglift": 1.6382
      },
      {
        "term": "quantitativ",
        "freq": 1.12,
        "total": 2.27,
        "logprob": -5.3136,
        "loglift": 1.6215
      },
      {
        "term": "differenzierung",
        "freq": 1.12,
        "total": 2.28,
        "logprob": -5.313,
        "loglift": 1.6201
      },
      {
        "term": "arbeitsteilig",
        "freq": 1.12,
        "total": 2.28,
        "logprob": -5.3136,
        "loglift": 1.62
      },
      {
        "term": "fakultativ",
        "freq": 1.11,
        "total": 2.27,
        "logprob": -5.322,
        "loglift": 1.6151
      },
      {
        "term": "frei",
        "freq": 1.12,
        "total": 2.3,
        "logprob": -5.3198,
        "loglift": 1.603
      },
      {
        "term": "unterstützung",
        "freq": 4.67,
        "total": 9.77,
        "logprob": -3.8875,
        "loglift": 1.5888
      },
      {
        "term": "lernorte",
        "freq": 1.1,
        "total": 2.32,
        "logprob": -5.3355,
        "loglift": 1.5805
      },
      {
        "term": "diskriminierung",
        "freq": 8.78,
        "total": 20.4,
        "logprob": -3.2567,
        "loglift": 1.4836
      },
      {
        "term": "gruppe",
        "freq": 4.91,
        "total": 11.61,
        "logprob": -3.8392,
        "loglift": 1.4649
      },
      {
        "term": "musik",
        "freq": 1.06,
        "total": 2.53,
        "logprob": -5.3755,
        "loglift": 1.4527
      },
      {
        "term": "gerechtigkeit",
        "freq": 4.67,
        "total": 11.24,
        "logprob": -3.8881,
        "loglift": 1.4481
      },
      {
        "term": "terror",
        "freq": 4.46,
        "total": 11.68,
        "logprob": -3.9344,
        "loglift": 1.3634
      },
      {
        "term": "legitimität",
        "freq": 4.68,
        "total": 12.84,
        "logprob": -3.8872,
        "loglift": 1.3159
      },
      {
        "term": "rassistisch",
        "freq": 5.5,
        "total": 15.38,
        "logprob": -3.7257,
        "loglift": 1.297
      },
      {
        "term": "stereotyp",
        "freq": 4.46,
        "total": 12.78,
        "logprob": -3.9342,
        "loglift": 1.2735
      },
      {
        "term": "betroffener",
        "freq": 4.46,
        "total": 13.31,
        "logprob": -3.9343,
        "loglift": 1.233
      },
      {
        "term": "umgang",
        "freq": 4.96,
        "total": 14.81,
        "logprob": -3.8277,
        "loglift": 1.2328
      },
      {
        "term": "migration",
        "freq": 4.78,
        "total": 14.52,
        "logprob": -3.8645,
        "loglift": 1.2157
      },
      {
        "term": "engagement",
        "freq": 4.68,
        "total": 14.68,
        "logprob": -3.8874,
        "loglift": 1.1817
      },
      {
        "term": "auswirkung",
        "freq": 4.46,
        "total": 14.28,
        "logprob": -3.9342,
        "loglift": 1.1628
      },
      {
        "term": "ursache",
        "freq": 5.06,
        "total": 18.78,
        "logprob": -3.8084,
        "loglift": 1.0145
      },
      {
        "term": "diversität",
        "freq": 4.63,
        "total": 17.83,
        "logprob": -3.8971,
        "loglift": 0.978
      },
      {
        "term": "europa",
        "freq": 4.84,
        "total": 20.65,
        "logprob": -3.8519,
        "loglift": 0.876
      },
      {
        "term": "gesellschaftlich",
        "freq": 5.46,
        "total": 28.51,
        "logprob": -3.7315,
        "loglift": 0.6741
      },
      {
        "term": "sozialisation",
        "freq": 4.4,
        "total": 20.81,
        "logprob": -3.948,
        "loglift": 0.7726
      },
      {
        "term": "demokratie",
        "freq": 4.52,
        "total": 48.95,
        "logprob": -3.9215,
        "loglift": -0.0566
      },
      {
        "term": "antisemitismus",
        "freq": 4.74,
        "total": 57.65,
        "logprob": -3.8741,
        "loglift": -0.1727
      }
    ],
    "9": [
      {
        "term": "auseinandersetzung",
        "freq": 22.23,
        "total": 23.7,
        "logprob": -3.0736,
        "loglift": 1.5166
      },
      {
        "term": "imperialismus",
        "freq": 12.58,
        "total": 13.68,
        "logprob": -3.6432,
        "loglift": 1.497
      },
      {
        "term": "holocaust",
        "freq": 15.44,
        "total": 18.18,
        "logprob": -3.4384,
        "loglift": 1.4168
      },
      {
        "term": "europäisch",
        "freq": 5.81,
        "total": 6.91,
        "logprob": -4.4151,
        "loglift": 1.4082
      },
      {
        "term": "afrika",
        "freq": 5.32,
        "total": 6.39,
        "logprob": -4.5045,
        "loglift": 1.3968
      },
      {
        "term": "deutschland",
        "freq": 16.38,
        "total": 19.75,
        "logprob": -3.3792,
        "loglift": 1.3933
      },
      {
        "term": "nsdiktatur",
        "freq": 20.93,
        "total": 25.96,
        "logprob": -3.1338,
        "loglift": 1.3655
      },
      {
        "term": "folge",
        "freq": 4.2,
        "total": 5.33,
        "logprob": -4.7398,
        "loglift": 1.3425
      },
      {
        "term": "weltkrieg",
        "freq": 18.14,
        "total": 23.38,
        "logprob": -3.2768,
        "loglift": 1.3269
      },
      {
        "term": "jude",
        "freq": 3.73,
        "total": 4.83,
        "logprob": -4.8584,
        "loglift": 1.3234
      },
      {
        "term": "widerstand",
        "freq": 15.43,
        "total": 20.14,
        "logprob": -3.4386,
        "loglift": 1.3146
      },
      {
        "term": "neuzeit",
        "freq": 3.21,
        "total": 4.3,
        "logprob": -5.0087,
        "loglift": 1.2888
      },
      {
        "term": "möglichkeit",
        "freq": 13.88,
        "total": 18.73,
        "logprob": -3.545,
        "loglift": 1.2807
      },
      {
        "term": "welt",
        "freq": 7.54,
        "total": 10.21,
        "logprob": -4.1545,
        "loglift": 1.2778
      },
      {
        "term": "nennen",
        "freq": 3.43,
        "total": 4.72,
        "logprob": -4.9422,
        "loglift": 1.261
      },
      {
        "term": "kolonie",
        "freq": 2.72,
        "total": 3.79,
        "logprob": -5.1754,
        "loglift": 1.2474
      },
      {
        "term": "system",
        "freq": 2.71,
        "total": 3.8,
        "logprob": -5.1794,
        "loglift": 1.242
      },
      {
        "term": "bundesrepublik",
        "freq": 2.69,
        "total": 3.78,
        "logprob": -5.1858,
        "loglift": 1.2414
      },
      {
        "term": "nsideologie",
        "freq": 10.27,
        "total": 15.3,
        "logprob": -3.8463,
        "loglift": 1.1819
      },
      {
        "term": "bürgerrecht",
        "freq": 3.38,
        "total": 5.03,
        "logprob": -4.9586,
        "loglift": 1.1814
      },
      {
        "term": "errichtung",
        "freq": 11.3,
        "total": 17.02,
        "logprob": -3.75,
        "loglift": 1.1716
      },
      {
        "term": "verschieden",
        "freq": 10.71,
        "total": 17.6,
        "logprob": -3.8035,
        "loglift": 1.0843
      },
      {
        "term": "demokratie",
        "freq": 29.6,
        "total": 48.95,
        "logprob": -2.7874,
        "loglift": 1.0775
      },
      {
        "term": "gewalt",
        "freq": 12.49,
        "total": 20.84,
        "logprob": -3.65,
        "loglift": 1.0689
      },
      {
        "term": "beurteilen",
        "freq": 3.55,
        "total": 6.03,
        "logprob": -4.9069,
        "loglift": 1.0517
      },
      {
        "term": "form",
        "freq": 14.88,
        "total": 25.29,
        "logprob": -3.4749,
        "loglift": 1.0502
      },
      {
        "term": "extremismus",
        "freq": 10.2,
        "total": 18.59,
        "logprob": -3.8524,
        "loglift": 0.981
      },
      {
        "term": "projekt",
        "freq": 6.21,
        "total": 11.4,
        "logprob": -4.3492,
        "loglift": 0.9734
      },
      {
        "term": "diktatur",
        "freq": 12.43,
        "total": 23.0,
        "logprob": -3.6551,
        "loglift": 0.9652
      },
      {
        "term": "aktiv",
        "freq": 2.16,
        "total": 4.07,
        "logprob": -5.406,
        "loglift": 0.9454
      },
      {
        "term": "antisemitismus",
        "freq": 20.31,
        "total": 57.65,
        "logprob": -3.1638,
        "loglift": 0.5376
      },
      {
        "term": "nationalsozialismus",
        "freq": 13.73,
        "total": 64.23,
        "logprob": -3.5558,
        "loglift": 0.0375
      },
      {
        "term": "bewert",
        "freq": 6.21,
        "total": 18.86,
        "logprob": -4.3492,
        "loglift": 0.4693
      },
      {
        "term": "charakterisieren",
        "freq": 5.42,
        "total": 16.78,
        "logprob": -4.4845,
        "loglift": 0.4512
      },
      {
        "term": "nationalsozialistisch",
        "freq": 5.83,
        "total": 21.0,
        "logprob": -4.4113,
        "loglift": 0.2999
      },
      {
        "term": "analysieren",
        "freq": 4.96,
        "total": 17.96,
        "logprob": -4.5745,
        "loglift": 0.2931
      },
      {
        "term": "wert",
        "freq": 4.08,
        "total": 10.93,
        "logprob": -4.7696,
        "loglift": 0.5945
      },
      {
        "term": "inhalt",
        "freq": 4.44,
        "total": 22.46,
        "logprob": -4.6837,
        "loglift": -0.0397
      },
      {
        "term": "menschenrecht",
        "freq": 3.87,
        "total": 13.33,
        "logprob": -4.8217,
        "loglift": 0.3438
      }
    ],
    "10": [
      {
        "term": "sexismus",
        "freq": 2.06,
        "total": 4.75,
        "logprob": -3.5591,
        "loglift": 2.6375
      },
      {
        "term": "wirksamkeit",
        "freq": 1.43,
        "total": 3.51,
        "logprob": -3.919,
        "loglift": 2.5815
      },
      {
        "term": "medium",
        "freq": 1.67,
        "total": 4.45,
        "logprob": -3.767,
        "loglift": 2.4965
      },
      {
        "term": "grundlegend",
        "freq": 2.05,
        "total": 5.72,
        "logprob": -3.5623,
        "loglift": 2.4494
      },
      {
        "term": "demokratisch",
        "freq": 5.84,
        "total": 18.83,
        "logprob": -2.5149,
        "loglift": 2.3054
      },
      {
        "term": "vergleich",
        "freq": 0.79,
        "total": 3.05,
        "logprob": -4.5195,
        "loglift": 2.121
      },
      {
        "term": "populismus",
        "freq": 1.32,
        "total": 5.36,
        "logprob": -4.0025,
        "loglift": 2.0739
      },
      {
        "term": "rechtsextremismus",
        "freq": 0.79,
        "total": 3.66,
        "logprob": -4.5188,
        "loglift": 1.9403
      },
      {
        "term": "diskutieren",
        "freq": 1.43,
        "total": 6.95,
        "logprob": -3.9194,
        "loglift": 1.898
      },
      {
        "term": "möglichkeit",
        "freq": 3.85,
        "total": 18.73,
        "logprob": -2.933,
        "loglift": 1.8927
      },
      {
        "term": "ausgrenzung",
        "freq": 1.43,
        "total": 7.05,
        "logprob": -3.9214,
        "loglift": 1.8817
      },
      {
        "term": "kennen",
        "freq": 0.79,
        "total": 4.0,
        "logprob": -4.5144,
        "loglift": 1.854
      },
      {
        "term": "ziel",
        "freq": 1.0,
        "total": 6.02,
        "logprob": -4.2753,
        "loglift": 1.6852
      },
      {
        "term": "jugendliche",
        "freq": 0.79,
        "total": 5.27,
        "logprob": -4.5161,
        "loglift": 1.5777
      },
      {
        "term": "grundgesetz",
        "freq": 1.82,
        "total": 12.47,
        "logprob": -3.6785,
        "loglift": 1.5537
      },
      {
        "term": "deutsch",
        "freq": 1.43,
        "total": 10.12,
        "logprob": -3.9212,
        "loglift": 1.5199
      },
      {
        "term": "produkt",
        "freq": 0.79,
        "total": 5.72,
        "logprob": -4.5183,
        "loglift": 1.4935
      },
      {
        "term": "engagement",
        "freq": 1.83,
        "total": 14.68,
        "logprob": -3.6732,
        "loglift": 1.3959
      },
      {
        "term": "jahrhundert",
        "freq": 0.91,
        "total": 7.49,
        "logprob": -4.3787,
        "loglift": 1.3633
      },
      {
        "term": "lernen",
        "freq": 0.79,
        "total": 6.92,
        "logprob": -4.521,
        "loglift": 1.3002
      },
      {
        "term": "sozial",
        "freq": 0.8,
        "total": 7.62,
        "logprob": -4.505,
        "loglift": 1.22
      },
      {
        "term": "umgang",
        "freq": 1.45,
        "total": 14.81,
        "logprob": -3.9111,
        "loglift": 1.1494
      },
      {
        "term": "analysieren",
        "freq": 1.43,
        "total": 17.96,
        "logprob": -3.921,
        "loglift": 0.9467
      },
      {
        "term": "kultur",
        "freq": 0.78,
        "total": 10.06,
        "logprob": -4.5283,
        "loglift": 0.9186
      },
      {
        "term": "thema",
        "freq": 0.96,
        "total": 14.48,
        "logprob": -4.3161,
        "loglift": 0.7671
      },
      {
        "term": "quantitativ",
        "freq": 0.15,
        "total": 2.27,
        "logprob": -6.2018,
        "loglift": 0.7333
      },
      {
        "term": "differenzierung",
        "freq": 0.14,
        "total": 2.28,
        "logprob": -6.2172,
        "loglift": 0.716
      },
      {
        "term": "arbeitsteilig",
        "freq": 0.14,
        "total": 2.28,
        "logprob": -6.2251,
        "loglift": 0.7084
      },
      {
        "term": "frei",
        "freq": 0.14,
        "total": 2.3,
        "logprob": -6.2262,
        "loglift": 0.6967
      },
      {
        "term": "lernorte",
        "freq": 0.14,
        "total": 2.32,
        "logprob": -6.221,
        "loglift": 0.6951
      },
      {
        "term": "gesellschaftlich",
        "freq": 1.44,
        "total": 28.51,
        "logprob": -3.9164,
        "loglift": 0.4892
      },
      {
        "term": "demokratie",
        "freq": 2.17,
        "total": 48.95,
        "logprob": -3.506,
        "loglift": 0.359
      },
      {
        "term": "antisemitismus",
        "freq": 1.45,
        "total": 57.65,
        "logprob": -3.9114,
        "loglift": -0.21
      },
      {
        "term": "ungleichheit",
        "freq": 0.15,
        "total": 2.71,
        "logprob": -6.1833,
        "loglift": 0.577
      },
      {
        "term": "zukunft",
        "freq": 0.16,
        "total": 4.14,
        "logprob": -6.1297,
        "loglift": 0.2048
      },
      {
        "term": "bezug",
        "freq": 0.18,
        "total": 15.85,
        "logprob": -6.0128,
        "loglift": -1.0204
      },
      {
        "term": "emanzipation",
        "freq": 0.16,
        "total": 8.1,
        "logprob": -6.127,
        "loglift": -0.4629
      }
    ]
  }
}